Workbook

Sheet Read Me
B2: SmallPlaneValue — Avionics Adjustment Engine
B3: Turns the equipment checklist into deterministic dollar adjustments. No AI guesses a price here — every figure traces to a coefficient you control.
B5: THE FORMULA (per item, per aircraft)
B6: value_add = Installed Cost × MAX( Floor% , Retained%(new) × (1 − Annual Decay%) ^ Years Since Install )
B7: • Installed Cost — typical all-in installed price for THIS airframe class (the big driver; varies a lot by aircraft, so treat as a range midpoint).
B8: • Retained%(new) — fraction of install cost that shows up in resale when the gear is recent. Avionics typically return ~30–70%, never 100%.
B9: • Annual Decay% — how that retained fraction erodes per year as the gear ages and newer boxes appear.
B10: • Floor% — the value never decays to zero; a working IFR navigator or autopilot keeps a capability floor. This sets the ceiling on decay.
B12: THREE RULES THAT SIT ON TOP OF THE TABLE
B13: 1) ADS-B OUT GATE. Since the Jan-2020 mandate, ADS-B Out is table stakes, not a premium. If the panel has NO ADS-B Out source, apply the
B14: 'ADS-B Out NON-COMPLIANT (penalty)' row — a negative adjustment (~cost to bring compliant + market stigma). Compliance earns $0 bonus; non-compliance is a discount.
B15: 2) IFR CAPABILITY BUNDLE. If the panel has BOTH an LPV-capable navigator AND a coupled (digital/approach-capable) autopilot, add a small bundle
... B28: and replace these blue inputs with fitted values. That closes the loop and makes the moat real. Everything blue is meant to be overwritten.

Sheet Avionics Adjustments
A1: Category | B1: Item / Model | C1: Installed Cost ($) | D1: Retained % (new) | E1: Annual Decay % | F1: Floor % | G1: Yrs Since Install | H1: Current Value Add ($) | I1: LPV/WAAS | J1: ADS-B Out | K1: ADS-B In | L1: Coupled AP | M1: Glass PFD | N1: Checkbox ID | O1: Notes / Source
A2: Navigator — GPS/Nav/Comm | B2: Garmin GTN 750Xi | C2: 26000 | D2: 0.6 | E2: 0.05 | F2: 0.35 | G2: 3 | H2: =C2*MAX(F2,D2*(1-E2)^G2) -> 13375.05 | I2: 1 | J2: 0 | K2: 0 | L2: 0 | M2: 0 | N2: nav_gtn750xi | O2: Unit $17,995 + install. Panel centerpiece, holds value. Garmin/Flying 2025.
A3: Navigator — GPS/Nav/Comm | B3: Garmin GTN 650Xi | C3: 19000 | D3: 0.6 | E3: 0.05 | F3: 0.35 | G3: 3 | H3: =C3*MAX(F3,D3*(1-E3)^G3) -> 9774.075 | I3: 1 | J3: 0 | K3: 0 | L3: 0 | M3: 0 | N3: nav_gtn650xi | O3: Unit $12,495 + install. Garmin/Flying 2025.
A4: Navigator — GPS/Nav/Comm | B4: Garmin GTN 750 (legacy) | C4: 18000 | D4: 0.45 | E4: 0.06 | F4: 0.25 | G4: 8 | H4: =C4*MAX(F4,D4*(1-E4)^G4) -> 4937.5084 | I4: 1 | J4: 0 | K4: 0 | L4: 0 | M4: 0 | N4: nav_gtn750 | O4: Pre-Xi; still desirable WAAS/LPV.
A5: Navigator — GPS/Nav/Comm | B5: Garmin GTN 650 (legacy) | C5: 13000 | D5: 0.45 | E5: 0.06 | F5: 0.25 | G5: 8 | H5: =C5*MAX(F5,D5*(1-E5)^G5) -> 3565.9783 | I5: 1 | J5: 0 | K5: 0 | L5: 0 | M5: 0 | N5: nav_gtn650 | O5: Pre-Xi.
A6: Navigator — GPS/Nav/Comm | B6: Garmin GNS 530W | C6: 11000 | D6: 0.4 | E6: 0.06 | F6: 0.2 | G6: 15 | H6: =C6*MAX(F6,D6*(1-E6)^G6) -> 2200 | I6: 1 | J6: 0 | K6: 0 | L6: 0 | M6: 0 | N6: nav_gns530w | O6: Legacy WAAS; LPV-capable but aging.
A7: Navigator — GPS/Nav/Comm | B7: Garmin GNS 430W | C7: 8000 | D7: 0.4 | E7: 0.06 | F7: 0.2 | G7: 15 | H7: =C7*MAX(F7,D7*(1-E7)^G7) -> 1600 | I7: 1 | J7: 0 | K7: 0 | L7: 0 | M7: 0 | N7: nav_gns430w | O7: Legacy WAAS.
A8: Navigator — GPS/Comm | B8: Garmin GNC 355 | C8: 12000 | D8: 0.5 | E8: 0.06 | F8: 0.3 | G8: 3 | H8: =C8*MAX(F8,D8*(1-E8)^G8) -> 4983.504 | I8: 1 | J8: 0 | K8: 0 | L8: 0 | M8: 0 | N8: nav_gnc355 | O8: GPS/Comm, LPV, no VOR/ILS. Unit ~$7,895.
A9: Navigator — GPS + ADS-B xpdr | B9: Garmin GNX 375 | C9: 13000 | D9: 0.5 | E9: 0.06 | F9: 0.3 | G9: 3 | H9: =C9*MAX(F9,D9*(1-E9)^G9) -> 5398.796 | I9: 1 | J9: 1 | K9: 1 | L9: 0 | M9: 0 | N9: nav_gnx375 | O9: GPS nav + 1090ES ADS-B In/Out. Unit ~$8,625.
A10: Navigator — GPS only | B10: Garmin GPS 175 | C10: 9000 | D10: 0.48 | E10: 0.06 | F10: 0.28 | G10: 3 | H10: =C10*MAX(F10,D10*(1-E10)^G10) -> 3588.1229 | I10: 1 | J10: 0 | K10: 0 | L10: 0 | M10: 0 | N10: nav_gps175 | O10: GPS-only, LPV; pairs w/ existing nav/comm.
A11: Navigator — GPS/Nav/Comm | B11: Avidyne IFD540 | C11: 16000 | D11: 0.45 | E11: 0.06 | F11: 0.25 | G11: 6 | H11: =C11*MAX(F11,D11*(1-E11)^G11) -> 4967.0624 | I11: 1 | J11: 0 | K11: 0 | L11: 0 | M11: 0 | N11: nav_ifd540 | O11: GTN 750 slide-in competitor.
A12: Navigator — GPS/Nav/Comm | B12: Avidyne IFD440 | C12: 12000 | D12: 0.45 | E12: 0.06 | F12: 0.25 | G12: 6 | H12: =C12*MAX(F12,D12*(1-E12)^G12) -> 3725.2968 | I12: 1 | J12: 0 | K12: 0 | L12: 0 | M12: 0 | N12: nav_ifd440 | O12: GTN 650 competitor.
A13: Glass — PFD/MFD | B13: Garmin G500 TXi (10.6") | C13: 19000 | D13: 0.55 | E13: 0.06 | F13: 0.3 | G13: 4 | H13: =C13*MAX(F13,D13*(1-E13)^G13) -> 8158.8266 | I13: 0 | J13: 0 | K13: 0 | L13: 0 | M13: 1 | N13: pfd_g500txi | O13: Large-format glass.
... A45: Traffic | B45: Active traffic (GTS 800 / Skywatch) | C45: 10000 | D45: 0.35 | E45: 0.08 | F45: 0.15 | G45: 8 | H45: =C45*MAX(F45,D45*(1-E45)^G45) -> 1796.2661 | I45: 0 | J45: 0 | K45: 0 | L45: 0 | M45: 0 | N45: traffic_active | O45: Active TAS; modest premium over ADS-B In.

Sheet Worked Example
A1: WORKED EXAMPLE — Beechcraft A36 Bonanza (illustrative panel)
A2: Edit the blue cells. Item names must match the 'Avionics Adjustments' sheet exactly. Rates auto-pull via VLOOKUP (green).
A4: Selected Item | B4: Qty | C4: Yrs | D4: Installed Cost (ea) | E4: Retained % (new) | F4: Decay % | G4: Floor % | H4: Value Add ($)
A5: Garmin GTN 750Xi | B5: 1 | C5: 3 | D5: =VLOOKUP($A5,'Avionics Adjustments'!$B:$H,2,0) -> 26000 | E5: =VLOOKUP($A5,'Avionics Adjustments'!$B:$H,3,0) -> 0.6 | F5: =VLOOKUP($A5,'Avionics Adjustments'!$B:$H,4,0) -> 0.05 | G5: =VLOOKUP($A5,'Avionics Adjustments'!$B:$H,5,0) -> 0.35 | H5: =B5*D5*MAX(G5,E5*(1-F5)^C5) -> 13375.05
A6: Garmin GI 275 (each) | B6: 2 | C6: 3 | D6: =VLOOKUP($A6,'Avionics Adjustments'!$B:$H,2,0) -> 6000 | E6: =VLOOKUP($A6,'Avionics Adjustments'!$B:$H,3,0) -> 0.5 | F6: =VLOOKUP($A6,'Avionics Adjustments'!$B:$H,4,0) -> 0.06 | G6: =VLOOKUP($A6,'Avionics Adjustments'!$B:$H,5,0) -> 0.3 | H6: =B6*D6*MAX(G6,E6*(1-F6)^C6) -> 4983.504
A7: Garmin GFC 500 (2-axis) | B7: 1 | C7: 4 | D7: =VLOOKUP($A7,'Avionics Adjustments'!$B:$H,2,0) -> 18000 | E7: =VLOOKUP($A7,'Avionics Adjustments'!$B:$H,3,0) -> 0.6 | F7: =VLOOKUP($A7,'Avionics Adjustments'!$B:$H,4,0) -> 0.05 | G7: =VLOOKUP($A7,'Avionics Adjustments'!$B:$H,5,0) -> 0.35 | H7: =B7*D7*MAX(G7,E7*(1-F7)^C7) -> 8796.6675
A8: Garmin GTX 345 (1090ES In/Out) | B8: 1 | C8: 4 | D8: =VLOOKUP($A8,'Avionics Adjustments'!$B:$H,2,0) -> 6500 | E8: =VLOOKUP($A8,'Avionics Adjustments'!$B:$H,3,0) -> 0.45 | F8: =VLOOKUP($A8,'Avionics Adjustments'!$B:$H,4,0) -> 0.07 | G8: =VLOOKUP($A8,'Avionics Adjustments'!$B:$H,5,0) -> 0.2 | H8: =B8*D8*MAX(G8,E8*(1-F8)^C8) -> 2188.0521
A9: JPI EDM 900 | B9: 1 | C9: 4 | D9: =VLOOKUP($A9,'Avionics Adjustments'!$B:$H,2,0) -> 5500 | E9: =VLOOKUP($A9,'Avionics Adjustments'!$B:$H,3,0) -> 0.5 | F9: =VLOOKUP($A9,'Avionics Adjustments'!$B:$H,4,0) -> 0.06 | G9: =VLOOKUP($A9,'Avionics Adjustments'!$B:$H,5,0) -> 0.3 | H9: =B9*D9*MAX(G9,E9*(1-F9)^C9) -> 2147.0596
A10: Garmin GMA 345 (Bluetooth) | B10: 1 | C10: 4 | D10: =VLOOKUP($A10,'Avionics Adjustments'!$B:$H,2,0) -> 3500 | E10: =VLOOKUP($A10,'Avionics Adjustments'!$B:$H,3,0) -> 0.4 | F10: =VLOOKUP($A10,'Avionics Adjustments'!$B:$H,4,0) -> 0.07 | G10: =VLOOKUP($A10,'Avionics Adjustments'!$B:$H,5,0) -> 0.2 | H10: =B10*D10*MAX(G10,E10*(1-F10)^C10) -> 1047.2728
A12: Sum of avionics adds | H12: =SUM(H5:H10) -> 32537.606
A13: IFR capability bundle bonus (LPV nav + coupled AP present) — input | H13: 2500
A14: Raw avionics value | H14: =H12+H13 -> 35037.606
A15: Base airframe value (year/engine/hours-adjusted) — input | H15: 260000
A16: Airframe cap on avionics (% of base) — input | H16: 0.4
A17: Cap amount | H17: =H15*H16 -> 104000
A18: Applied avionics value (min of raw vs cap) | H18: =MIN(H14,H17) -> 35037.606
A20: ESTIMATED VALUE = base airframe + applied avionics | H20: =H15+H18 -> 295037.61
A22: Note: illustrative only. Base airframe figure is a placeholder — your year-based pricing engine supplies it. The avionics layer is what this workbook computes.
